optbinning/__init__.py
optbinning/_version.py
optbinning/exceptions.py
optbinning/formatting.py
optbinning/information.py
optbinning/logging.py
optbinning/options.py
optbinning/binning/__init__.py
optbinning/binning/auto_monotonic.py
optbinning/binning/base.py
optbinning/binning/binning.py
optbinning/binning/binning_information.py
optbinning/binning/binning_process.py
optbinning/binning/binning_process_information.py
optbinning/binning/binning_statistics.py
optbinning/binning/continuous_binning.py
optbinning/binning/continuous_cp.py
optbinning/binning/cp.py
optbinning/binning/ls.py
optbinning/binning/mdlp.py
optbinning/binning/metrics.py
optbinning/binning/mip.py
optbinning/binning/model_data.py
optbinning/binning/multiclass_binning.py
optbinning/binning/multiclass_cp.py
optbinning/binning/multiclass_mip.py
optbinning/binning/outlier.py
optbinning/binning/prebinning.py
optbinning/binning/preprocessing.py
optbinning/binning/transformations.py
optbinning/binning/distributed/__init__.py
optbinning/binning/distributed/base.py
optbinning/binning/distributed/binning_process_sketch.py
optbinning/binning/distributed/binning_process_sketch_information.py
optbinning/binning/distributed/binning_sketch.py
optbinning/binning/distributed/bsketch.py
optbinning/binning/distributed/bsketch_information.py
optbinning/binning/distributed/gk.py
optbinning/binning/distributed/plots.py
optbinning/binning/multidimensional/__init__.py
optbinning/binning/multidimensional/binning_2d.py
optbinning/binning/multidimensional/binning_statistics_2d.py
optbinning/binning/multidimensional/continuous_binning_2d.py
optbinning/binning/multidimensional/cp_2d.py
optbinning/binning/multidimensional/mip_2d.py
optbinning/binning/multidimensional/model_data_2d.py
optbinning/binning/multidimensional/model_data_cart_2d.py
optbinning/binning/multidimensional/preprocessing_2d.py
optbinning/binning/multidimensional/transformations_2d.py
optbinning/binning/piecewise/__init__.py
optbinning/binning/piecewise/base.py
optbinning-0.20.1.dist-info/LICENSE
optbinning-0.20.1.dist-info/METADATA
optbinning-0.20.1.dist-info/WHEEL
optbinning-0.20.1.dist-info/top_level.txt
optbinning-0.20.1.dist-info/RECORD
