Metadata-Version: 2.1
Name: optbinning
Version: 0.20.1
Summary: OptBinning: The Python Optimal Binning library
Home-page: https://github.com/guillermo-navas-palencia/optbinning
Author: Guillermo Navas-Palencia
Author-email: g.navas.palencia@gmail.com
License: Apache Licence 2.0
Platform: any
Classifier: Topic :: Scientific/Engineering :: Mathematics
Classifier: Topic :: Software Development :: Libraries
Classifier: Topic :: Software Development :: Libraries :: Python Modules
Classifier: Intended Audience :: Developers
Classifier: Intended Audience :: Education
Classifier: Intended Audience :: Science/Research
Classifier: License :: OSI Approved :: Apache Software License
Classifier: Programming Language :: Python :: 3
Classifier: Programming Language :: Python :: 3.9
Classifier: Programming Language :: Python :: 3.10
Classifier: Programming Language :: Python :: 3.11
Classifier: Programming Language :: Python :: 3.12
Requires-Python: >=3.7
Provides-Extra: distributed
Provides-Extra: test
Provides-Extra: ecos
